enp/__init__.py
enp/linalg/__init__.py
enp/linalg/linear_algebra.py
enp/linalg/linear_algebra_additional.py
enp/linalg/linear_algebra_utils.py
enp/ml/__init__.py
enp/ml/kmeans.py
enp/ml/linear_regression.py
enp/ml/logistic_regression.py
enp/nn/__init__.py
enp/nn/activations.py
enp/nn/conv2d_layer.py
enp/nn/linear_layer.py
enp/nn/model.py
enp/nn/other_layers.py
tests/__init__.py
tests/test_linear_algebra.py
tests/test_linear_algebra_additional.py
enp-0.1.0.dist-info/METADATA
enp-0.1.0.dist-info/WHEEL
enp-0.1.0.dist-info/top_level.txt
enp-0.1.0.dist-info/RECORD
