Metadata-Version: 2.1
Name: enp
Version: 0.1.0
Summary: Implementation of deep learning, machine learning and math algorithms in NumPy and pure Python
Home-page: https://github.com/shlyapin/enp
Author: Alexander Shlyapin
Author-email: al.shlyapin@gmail.com
License: UNKNOWN
Project-URL: Bug Tracker, https://github.com/shlyapin/enp/issues
Platform: UNKNOWN
Classifier: Programming Language :: Python :: 3
Classifier: Operating System :: OS Independent
Requires-Python: >=3.6
Requires-Dist: numpy
